ssh_manager/__init__.py
ssh_manager/connection.py
ssh_manager/exception_handlers.py
ssh_manager/main.py
ssh_manager/parse_args.py
ssh_manager/routing.py
ssh_manager/runtime_exceptions.py
ssh_manager/shell.py
ssh_manager/stored/__init__.py
ssh_manager/stored/modify.py
ssh_manager/stored/read.py
ssh_manager/stored/store_path.py
ssh_manager/tmux.py
ssh_m_py-0.3.2.dist-info/LICENSE
ssh_m_py-0.3.2.dist-info/METADATA
ssh_m_py-0.3.2.dist-info/WHEEL
ssh_m_py-0.3.2.dist-info/entry_points.txt
ssh_m_py-0.3.2.dist-info/RECORD
