Metadata-Version: 2.1
Name: ssh_m.py
Version: 0.3.2
Summary: Keep all ssh connection next to you
Home-page: https://github.com/LoliPain/ssh_manager
License: MIT
Keywords: ssh-manager,ssh_m,ssh,connection-storage,ssh-cli-storage
Author: LoliPain
Author-email: x@lolipa.in
Requires-Python: >=3.10,<4.0
Classifier: Environment :: Console
Classifier: License :: OSI Approved :: MIT License
Classifier: Programming Language :: Python
Classifier: Programming Language :: Python :: 3
Classifier: Programming Language :: Python :: 3.10
Classifier: Programming Language :: Python :: 3.11
Classifier: Programming Language :: Python :: 3.12
Classifier: Topic :: System :: Networking
Classifier: Topic :: System :: Systems Administration
Classifier: Typing :: Typed
Requires-Dist: inquirerpy (>=0.3.4,<0.4.0)
Requires-Dist: pydantic (>=2.9.2,<3.0.0)
Project-URL: Repository, https://github.com/LoliPain/ssh_manager
